wired_tts.py
wired_tts-0.2.0.dist-info/LICENSE.txt
wired_tts-0.2.0.dist-info/METADATA
wired_tts-0.2.0.dist-info/RECORD
wired_tts-0.2.0.dist-info/WHEEL
wired_tts-0.2.0.dist-info/entry_points.txt
wired_tts-0.2.0.dist-info/top_level.txt
wired_tts-0.2.0.dist-info/zip-safe
